bilili/__init__.py
bilili/__main__.py
bilili/__version__.py
bilili/quality.py
bilili/tools.py
bilili/video.py
bilili/api/__init__.py
bilili/api/acg_video.py
bilili/api/bangumi.py
bilili/api/danmaku.py
bilili/api/exceptions.py
bilili/api/utils.py
bilili/api/vip.py
bilili/handlers/__init__.py
bilili/handlers/base.py
bilili/handlers/downloader.py
bilili/handlers/merger.py
bilili/handlers/status.py
bilili/parser/__init__.py
bilili/parser/acg_video.py
bilili/parser/bangumi.py
bilili/utils/__init__.py
bilili/utils/base.py
bilili/utils/crawler.py
bilili/utils/danmaku.py
bilili/utils/ffmpeg.py
bilili/utils/playlist.py
bilili/utils/subtitle.py
bilili/utils/thread.py
bilili/utils/console/__init__.py
bilili/utils/console/colorful.py
bilili/utils/console/logger.py
bilili/utils/console/ui.py
bilili/utils/functiontools/__init__.py
bilili/utils/functiontools/attrdict.py
bilili/utils/functiontools/singleton.py
bilili-1.4.15.dist-info/LICENSE
bilili-1.4.15.dist-info/METADATA
bilili-1.4.15.dist-info/WHEEL
bilili-1.4.15.dist-info/entry_points.txt
bilili-1.4.15.dist-info/top_level.txt
bilili-1.4.15.dist-info/RECORD
