Metadata-Version: 2.1
Name: bilili
Version: 1.4.15
Summary: 🍻 bilibili video and danmaku downloader | B站视频、弹幕下载器
Author-email: Nyakku Shigure <sigure.qaq@gmail.com>
License: GPLv3
Project-URL: Homepage, https://github.com/yutto-dev/bilili
Project-URL: Documentation, https://bilili.nyakku.moe/
Keywords: python,bilibili,video,download,spider,danmaku
Classifier: Environment :: Console
Classifier: Operating System :: OS Independent
Classifier: License :: OSI Approved :: GNU General Public License v3 (GPLv3)
Classifier: Programming Language :: Python
Classifier: Programming Language :: Python :: 3
Classifier: Programming Language :: Python :: 3.8
Classifier: Programming Language :: Python :: 3.9
Classifier: Programming Language :: Python :: 3.10
Classifier: Programming Language :: Python :: 3.11
Classifier: Programming Language :: Python :: 3.12
Classifier: Programming Language :: Python :: Implementation :: CPython
Requires-Python: >=3.8
License-File: LICENSE
Requires-Dist: requests
Requires-Dist: biliass ==1.3.7
Provides-Extra: dev
Requires-Dist: pytest >=7.4.0 ; extra == 'dev'
Requires-Dist: black >=23.9.1 ; extra == 'dev'
Requires-Dist: isort >=5.12.0 ; extra == 'dev'
Requires-Dist: ruff ==0.0.292 ; extra == 'dev'
Requires-Dist: pytest-rerunfailures >=11.0 ; extra == 'dev'
Requires-Dist: build ; extra == 'dev'
